{
  "film": {
    "title": "How to Train Your Dragon",
    "overview": "As the son of a Viking leader on the cusp of manhood, shy Hiccup Horrendous Haddock III faces a rite of passage: he must kill a dragon to prove his warrior mettle. But after downing a feared dragon, he realizes that he no longer wants to destroy it, and instead befriends the beast – which he names Toothless – much to the chagrin of his warrior father",
    "imageUrl": "https://image.tmdb.org/t/p/w600_and_h900_bestv2/hIXX3IRFy0InUOmYeWjvhCAgQNj.jpg",
    "imdbScore": "7.7",
    "trailerLink": "https://www.youtube.com/watch?v=IT_ufPxiXl8",
    "numberOfGenres": 4,
    "genres": {
      "0": "Fantasy",
      "1": "Adventure",
      "2": "Animation",
      "3": "Family"
    }
  }
}