{
  "film": {
    "title": "Never Surrender: A Galaxy Quest Documentary",
    "director": "Jack Bennett",
    "release_date": "2019-11-26",
    "film_id": 637963,
    "original_language": "English",
    "overview": "A feature-length documentary about the film Galaxy Quest and its legacy, celebrating its milestone 20th anniversary.",
    "imageUrl": "https://image.tmdb.org/t/p/w600_and_h900_bestv2/40Tje7U3S6LwNL2KRothPEmgw7H.jpg",
    "imdbScore": "6.8",
    "trailerLink": "https://www.youtube.com/watch?v=39cVvN28UXE",
    "numberOfGenres": 1,
    "watchOn": "Apple TV",
    "genres": {
      "0": "Documentary"
    },
    "lead_actors": [
      " Tim Allen",
      " Greg Berlanti",
      " Enrico Colantoni"
    ],
    "supporting_actors": [
      " Alan Rickman",
      " Sigourney Weaver",
      " Mark Johnson",
      " Damon Lindelof",
      " Daryl Mitchell",
      " Dean Parisot",
      " Wil Wheaton",
      " Justin Long"
    ]
  }
}