{
  "film": {
    "title": "Willy Wonka & the Chocolate Factory",
    "director": "Mel Stuart",
    "release_date": "1971-06-29",
    "film_id": 252,
    "original_language": "English",
    "spoken_languages": [
      " French",
      " English",
      " Italian",
      " German"
    ],
    "overview": "Eccentric candy man Willy Wonka prompts a worldwide frenzy when he announces that golden tickets hidden inside five of his delicious candy bars will admit their lucky holders into his top-secret confectionary. But does Wonka have an agenda hidden amid a world of Oompa Loompas and chocolate rivers?",
    "imageUrl": "https://image.tmdb.org/t/p/w600_and_h900_bestv2/avEUV2YWABEVqvpSjif0NKmTykS.jpg",
    "imdbScore": "7.5",
    "trailerLink": "https://www.youtube.com/watch?v=vxYKQoMt5TQ",
    "numberOfGenres": 3,
    "watchOn": "Apple TV",
    "genres": {
      "0": "Family",
      "1": "Fantasy",
      "2": "Comedy"
    },
    "lead_actors": [
      " Gene Wilder",
      " Peter Ostrum",
      " Jack Albertson"
    ],
    "supporting_actors": [
      " Roy Kinnear",
      " Julie Dawn Cole",
      " Leonard Stone",
      " Denise Nickerson",
      " Nora Denney",
      " Paris Themmen",
      " Ursula Reit",
      " Michael Bollner"
    ]
  }
}